enzope/__init__.py
enzope/graphs/__init__.py
enzope/graphs/custom_gtg.py
enzope/graphs/graph_class.py
enzope/kernels/__init__.py
enzope/kernels/k_ys.py
enzope/kernels/k_ys_gpt_features.py
enzope/kernels/locks.py
enzope/metrics/__init__.py
enzope/metrics/gpu_measures.py
enzope/metrics/measures.py
enzope/models/__init__.py
enzope/models/model.py
enzope/trades/__init__.py
enzope/trades/ys.py
enzope/utils/__init__.py
enzope/utils/misc.py
enzope/utils/plots.py
enzope-0.0.49.dist-info/METADATA
enzope-0.0.49.dist-info/WHEEL
enzope-0.0.49.dist-info/top_level.txt
enzope-0.0.49.dist-info/RECORD
